bsdl_parser/__init__.py
bsdl_parser/bsdl.py
bsdl_parser/bsdl2json.py
bsdl_parser/fast_bsdl_parser.py
bsdl_parser-0.1.1.dist-info/LICENSE
bsdl_parser-0.1.1.dist-info/METADATA
bsdl_parser-0.1.1.dist-info/WHEEL
bsdl_parser-0.1.1.dist-info/entry_points.txt
bsdl_parser-0.1.1.dist-info/top_level.txt
bsdl_parser-0.1.1.dist-info/RECORD
